README.rst
setup.cfg
setup.py
./__init__.py
./product.py
./product.xml
./tryton.cfg
./tests/__init__.py
./tests/test_product.py
trytond_product_code.egg-info/PKG-INFO
trytond_product_code.egg-info/SOURCES.txt
trytond_product_code.egg-info/dependency_links.txt
trytond_product_code.egg-info/entry_points.txt
trytond_product_code.egg-info/not-zip-safe
trytond_product_code.egg-info/requires.txt
trytond_product_code.egg-info/top_level.txt